bitbucket_cloud_client_foolishnekozzz/__init__.py
bitbucket_cloud_client_foolishnekozzz/bitbucket_api.py
bitbucket_cloud_client_foolishnekozzz/requests_wrapper.py
bitbucket_cloud_client_foolishnekozzz-1.0.2.dist-info/LICENSE
bitbucket_cloud_client_foolishnekozzz-1.0.2.dist-info/METADATA
bitbucket_cloud_client_foolishnekozzz-1.0.2.dist-info/WHEEL
bitbucket_cloud_client_foolishnekozzz-1.0.2.dist-info/top_level.txt
bitbucket_cloud_client_foolishnekozzz-1.0.2.dist-info/RECORD
