Metadata-Version: 2.1
Name: bitbucket_cloud_client_foolishnekozzz
Version: 1.0.2
Summary: SDK for Bitbucket Cloud
Author-email: foolishnekozzz <foolishnekozzz@example.com>
Project-URL: Homepage, https://github.com/foolishnekozzz/bitbucket-cloud-client
Project-URL: Issues, https://github.com/foolishnekozzz/bitbucket-cloud-client/issues
Classifier: Programming Language :: Python :: 3
Classifier: License :: OSI Approved :: MIT License
Classifier: Operating System :: OS Independent
Requires-Python: >=3.8
License-File: LICENSE
